AI_TUI/__init__.py
AI_TUI/backend.py
AI_TUI/config_tools.py
AI_TUI/entry.py
AI_TUI/main.py
AI_TUI/tools/__init__.py
AI_TUI/tools/tools.py
ai_terminal_ui-1.0.2.dist-info/licenses/LICENSE
ai_terminal_ui-1.0.2.dist-info/METADATA
ai_terminal_ui-1.0.2.dist-info/WHEEL
ai_terminal_ui-1.0.2.dist-info/entry_points.txt
ai_terminal_ui-1.0.2.dist-info/top_level.txt
ai_terminal_ui-1.0.2.dist-info/RECORD
