Metadata-Version: 2.4
Name: AI-Terminal-UI
Version: 1.0.2
Summary: Allows users to use both the gemini and openai APIs in a nice and user-friendly terminal UI way.
Author-email: Username0103 <Username0103@users.noreply.github.com>
License: The MIT License (MIT)
Project-URL: homepage, https://github.com/Username0103/AI-TUI
Project-URL: issues, https://github.com/Username0103/AI-TUI/issues
Keywords: ai,tui,cli,ui,terminal,openai,openai-api,gemini,gemini-api,llm,chatgpt,chatbot,conversational-ai,generative-ai,ai-assistant,command-line,text-ui,terminal-app,prompt-toolkit
Classifier: Development Status :: 5 - Production/Stable
Classifier: Environment :: Console
Classifier: Intended Audience :: End Users/Desktop
Classifier: Intended Audience :: Developers
Classifier: Programming Language :: Python :: 3
Classifier: Operating System :: Microsoft :: Windows
Classifier: Operating System :: POSIX :: Linux
Classifier: Operating System :: MacOS
Classifier: Natural Language :: English
Classifier: Topic :: Utilities
Classifier: Topic :: Scientific/Engineering :: Artificial Intelligence
Requires-Python: >=3.10
License-File: LICENSE
Requires-Dist: openai>=1.76.0
Requires-Dist: google-genai>=1.12.1
Requires-Dist: prompt-toolkit>=3.0.51
Requires-Dist: mdv>=1.7.5
Requires-Dist: toml>=0.10.2
Requires-Dist: python-dotenv>=1.1.0
Requires-Dist: questionary>=2.1.0
Requires-Dist: requests>=2.32.3
Requires-Dist: pydantic>=2.11.3
Dynamic: license-file
